Workbook

Sheet Sheet1
A1: 流程
A2: 流程 | B2: 数据库 | C2: 表 | D2: 描述 | E2: 备注 | F2: nn | G2: csyy | H2: mxd | I2: dfd | J2: unifi | K2: maiya
A3: 短信验证 | B3: db_nono | C3: system_sms_log | D3: 短信发送日志表 | F3: 1 | G3: 0 | H3: 1 | I3: 1 | J3: 1 | K3: 0
A4: 短信验证 | B4: db_nono | C4: sms_channel_info | D4: 短信通道维表 | F4: 1 | G4: 0 | H4: 1 | I4: 1 | J4: 1 | K4: 0
A5: 短信验证 | B5: db_nono | C5: sms_task | D5: 后台定时短信任务 | F5: 1 | G5: 0 | H5: 1 | I5: 1 | J5: 1 | K5: 0
A6: 短信验证 | B6: db_nono | C6: sms_task_detail | D6: 后台定时短信任务明细 | F6: 1 | G6: 0 | H6: 1 | I6: 1 | J6: 1 | K6: 0
A7: 用户注册 | B7: db_nono | C7: user_info | D7: 用户基本信息 | F7: 1 | G7: 1 | H7: 1 | I7: 1 | J7: 1 | K7: 1
A8: 用户注册 | B8: db_nono | C8: user_info_detail | D8: 用户详细信息
A9: 促销

Sheet Sheet3
A1: 数据库 | B1: 表名 | C1: 表格描述 | D1: 行数 | E1: 创建时间 | F1: 人工备注 | G1: 新增行数
A2: db_nono | B2: InterestrateCut_template | C2: 减息券的模板 | D2: 62 | E2: 42315.694 | F2: 减息券的模板 | G2: -1
A3: db_nono | B3: MGT_ORG | D3: 0 | E3: 42185.93 | G3: 0
A4: db_nono | B4: MGT_RESOURCE | D4: 16 | E4: 42185.931 | G4: 0
A5: db_nono | B5: MGT_ROLE | D5: 3 | E5: 42185.931 | G5: 0
A6: db_nono | B6: MGT_ROLE_RESOURCE | D6: 9 | E6: 42185.931 | G6: 0
A7: db_nono | B7: MGT_USER | D7: 85 | E7: 42185.931 | G7: 0
A8: db_nono | B8: MGT_USER_ROLE | D8: 15 | E8: 42185.931 | G8: 0
A9: db_nono | B9: QRTZ_BLOB_TRIGGERS | D9: 0 | E9: 42185.932 | G9: 0
A10: db_nono | B10: QRTZ_CALENDARS | D10: 0 | E10: 42185.932 | G10: 0
A11: db_nono | B11: QRTZ_CRON_TRIGGERS | D11: 6 | E11: 42185.932 | G11: 0
A12: db_nono | B12: QRTZ_FIRED_TRIGGERS | D12: 1 | E12: 42185.932 | G12: 1
A13: db_nono | B13: QRTZ_JOB_DETAILS | D13: 6 | E13: 42185.932 | G13: 0
A14: db_nono | B14: QRTZ_LOCKS | D14: 2 | E14: 42185.932 | G14: 0
... A20: db_nono | B20: SCHEDULE_JOB | D20: 6 | E20: 42185.932 | G20: 0
A21: db_nono | B21: WeiXin_Qr_Code | C21: 微信二维码 | D21: 32 | E21: 42174.735 | F21: 微信二维码 | G21: 0
A22: db_nono | B22: account_relation | D22: 1896118 | E22: 42326.969 | G22: -25163
A23: db_nono | B23: action_log | C23: 操作日志表 | D23: 619046 | E23: 42247.784 | F23: 操作日志表 | G23: -567
A24: db_nono | B24: activity | C24: 活动表 | D24: 10 | E24: 42080.382 | F24: 活动表 | G24: 0
A25: db_nono | B25: activity_access_log | C25: 活动日志表 | D25: 3646 | E25: 42080.382 | F25: 财运活动表 | G25: 0
A26: db_nono | B26: activity_begging | D26: 31100 | E26: 42140.414 | G26: 0
A27: db_nono | B27: activity_begging_details | D27: 39828 | E27: 42140.415 | G27: 0
A28: db_nono | B28: activity_goods | C28: 活动商品表 | D28: 8 | E28: 42502.66 | F28: 活动商品表 | G28: 0
A29: db_nono | B29: activity_goods_log | C29: 商品库存修改记录表 | D29: 9 | E29: 42502.66 | F29: 商品库存修改记录表 | G29: 0
A30: db_nono | B30: activity_interest | C30: 活动收益表 | D30: 693 | E30: 42080.382 | F30: 大房东加息结果 | G30: 0
A31: db_nono | B31: activity_interest_details | C31: 活动收益详细信息表 | D31: 4042 | E31: 42080.382 | F31: 大房东加息详情 | G31: 0
A32: db_nono | B32: activity_interest_topic | C32: 活动页猜你感兴趣话题 | D32: 0 | E32: 42156.142 | F32: 活动页猜你感兴趣话题 | G32: 0
A33: db_nono | B33: activity_messages | C33: 活动消息表 | D33: 6019711 | E33: 42080.382 | F33: 每月精选收益短信发送记录 | G33: -113314
A34: db_nono | B34: activity_mobiles | C34: 活动手机号表 | D34: 3434997 | E34: 42080.382 | F34: 手机验证发送注册页 | G34: -28833
A35: db_nono | B35: activity_nbparty_user_info | D35: 41625 | E35: 42527.806 | G35: 0
A36: db_nono | B36: activity_point_log | D36: 7900826 | E36: 42331.622 | G36: -241467
A37: db_nono | B37: activity_point_log_back | D37: 32817272 | E37: 42499.666 | G37: 0
A38: db_nono | B38: activity_prize_gain_list | D38: 7340813 | E38: 42166.408 | G38: -214264
A39: db_nono | B39: activity_prize_gain_list_back | D39: 27192697 | E39: 42499.686 | G39: 0
A40: db_nono | B40: activity_prize_list | C40: 活动送礼表 | D40: 118 | E40: 42166.408 | F40: 活动送礼表 | G40: 0
A41: db_nono | B41: activity_prolocutor | C41: 镑客大使表(原表名prolocutor) | D41: 409479 | E41: 42156.142 | F41: 镑客大使表(原表名prolocutor) | G41: -1326
A42: db_nono | B42: activity_prolocutor_code | D42: 274209 | E42: 42192.655 | G42: -965
A43: db_nono | B43: activity_prolocutor_data | C43: 镑客大使数据表(原表名prolocutor_data) | D43: 0 | E43: 42156.142 | F43: 镑客大使数据表(原表名prolocutor_data) | G43: 0
A44: db_nono | B44: activity_red_packet | C44: 红包记录表 | D44: 66160 | E44: 42395.776 | F44: 红包记录表 | G44: 0
A45: db_nono | B45: activity_red_packet_gain_log | C45: 红包领取记录表 | D45: 968142 | E45: 42395.776 | F45: 红包领取记录表 | G45: 0
A46: db_nono | B46: activity_red_packet_resend_log | C46: 红包复发记录表 | D46: 37037 | E46: 42395.776 | F46: 红包复发记录表 | G46: 0
A47: db_nono | B47: activity_redrain | C47: 红包雨表 | D47: 3670 | E47: 42097.771 | F47: 客户获取红包总表 | G47: 0
A48: db_nono | B48: activity_redrain_details | C48: 红包雨详细信息表 | D48: 3639 | E48: 42097.771 | F48: 客户获取红包详情表 | G48: 0
A49: db_nono | B49: activity_redrain_mobiles | C49: qq红包活动用户手机号记录(原表名qq_activity_mobiles) | D49: 152 | E49: 42156.142 | F49: qq红包活动用户手机号记录(原表名qq_activity_mobiles) | G49: 0
A50: db_nono | B50: activity_seven_years_account | C50: 7周年活动用户账单表 | D50: 151945 | E50: 42523.413 | F50: 7周年活动用户账单表 | G50: 0
A51: db_nono | B51: activity_seven_years_percent_line | C51: 七周年用户投资百分比达标线 | D51: 553898 | E51: 42523.413 | F51: 七周年用户投资百分比达标线 | G51: -15437
A52: db_nono | B52: activity_statistic | C52: 活动统计表 | D52: 97935 | E52: 42080.382 | F52: 客户推荐链接点击客户ip信息 | G52: 0
A53: db_nono | B53: activity_user_goods | C53: 用户领取活动商品表 | D53: 6 | E53: 42502.66 | F53: 用户领取活动商品表 | G53: 0
A54: db_nono | B54: activity_vip | C54: 超镑活动表原表名：chaobang | D54: 329 | E54: 42156.142 | F54: 超镑活动表原表名：chaobang | G54: 3
... A81: db_nono | B81: america_school | C81: 美国学校信息表 | D81: 3004 | E81: 42482.005 | F81: 美国学校信息表 | G81: -4
A82: db_nono | B82: analyse_calendar | D82: 34 | E82: 42191.591 | G82: 0
A83: db_nono | B83: analyse_licai | D83: 378 | E83: 42191.583 | G83: 0
A84: db_nono | B84: app | C84: app信息 | D84: 0 | E84: 42303.49 | F84: app信息 | G84: 0
A85: db_nono | B85: app_pic | C85: app 图片表 | D85: 105 | E85: 42303.623 | F85: app 图片表 | G85: -6
A86: db_nono | B86: app_system | C86: app设备记录表 | D86: 1812 | E86: 42080.382 | F86: app设备记录表 | G86: 0
A87: db_nono | B87: app_upload_files | C87: app附件上传记录表 | D87: 1675603 | E87: 42080.685 | F87: 客户app上传资料 | G87: -18255
A88: db_nono | B88: app_version | C88: app版本信息表 | D88: 0 | E88: 42303.49 | F88: app版本信息表 | G88: 0
A89: db_nono | B89: app_visit_record | C89: app设备访问记录表 | D89: 2790 | E89: 42080.382 | F89: app设备访问记录表 | G89: 0
A90: db_nono | B90: articles | C90: 资讯表 | D90: 1597 | E90: 42080.382 | F90: 文章表 | G90: -21
A91: db_nono | B91: articles_cat | C91: 资讯分类表 | D91: 42 | E91: 42080.382 | F91: 资讯分类表 | G91: 0
A92: db_nono | B92: authen_author_log | C92: 开通鉴权表 | D92: 2076156 | E92: 42187.777 | F92: 开通鉴权表 | G92: -31444
A93: db_nono | B93: authentication_htsb | C93: 活体识别日志表(原表名borrows_prepare) | D93: 155254 | E93: 42156.143 | F93: 活体识别日志表(原表名borrows_prepare) | G93: 0
A94: db_nono | B94: authentication_htsb_log | C94: 活体识别日志表(原表名htsb_log) | D94: 713066 | E94: 42156.143 | F94: 活体识别日志表(原表名htsb_log) | G94: -36947
A95: db_nono | B95: autobid_log | C95: 精选&散投自动投标日志表 | D95: 5524722 | E95: 42080.382 | F95: 自动投标日志表 | G95: -111081
A96: db_nono | B96: ba_trigger_delta | D96: 18677820 | E96: 42609.929 | G96: -471693
A97: db_nono | B97: bank | C97: 银行省份关联表 | D97: 93536 | E97: 42156.144 | F97: 银行省份关联表 | G97: 0
A98: db_nono | B98: bank_card_info | C98: 银行卡信息表(原表名bank_info) | D98: 2144 | E98: 42156.144 | F98: 银行卡信息表(原表名bank_info) | G98: 0
A99: db_nono | B99: bank_code | C99: 镑客码 对应原数据库bankcode | D99: 54104 | E99: 42156.144 | F99: 镑客码 对应原数据库bankcode | G99: -2
A100: db_nono | B100: bank_code_model | C100: 镑客码模板表 | D100: 0 | E100: 42593.659 | F100: 镑客码模板表 | G100: 0
A101: db_nono | B101: bank_code_relation | D101: 25 | E101: 42326.969 | G101: 0
A102: db_nono | B102: bank_info | C102: 银行信息表(原表名bank_info_address) | D102: 2191 | E102: 42080.382 | F102: 银行信息表(原表名bank_info_address) | G102: 0
A103: db_nono | B103: bank_payment_warning | D103: 55 | E103: 42160.587 | G103: 0
A104: db_nono | B104: bill | C104: 账单表，计算所有人的账单 | D104: 43737 | E104: 42169.413 | F104: 账单表，计算所有人的账单 | G104: 0
A105: db_nono | B105: bill_recharges | C105: 快钱充值流水记录表 | D105: 183312 | E105: 42080.382 | F105: 快钱充值流水记录表 | G105: 0
A106: db_nono | B106: bill_repayment_history | C106: 账单还款记录表，每还一次款会在这里生成一条记录 | D106: 7408 | E106: 42169.413 | F106: 账单还款记录表，每还一次款会在这里生成一条记录 | G106: -16
A107: db_nono | B107: bill_wechat_pre | C107: 0元付账单微信二维码预支付参数表 | D107: 2103903 | E107: 42312.676 | F107: 0元付账单微信二维码预支付参数表 | G107: -55443
A108: db_nono | B108: bkds_temporary | D108: 25 | E108: 42416.869 | G108: 0
A109: db_nono | B109: black_gray_becheck_list | C109: 反欺诈黑灰名待复核库 | D109: 0 | E109: 42592.771 | F109: 反欺诈黑灰名待复核库 | G109: 0
A110: db_nono | B110: black_gray_check_log | C110: 反欺诈待复核操作日志 | D110: 0 | E110: 42592.771 | F110: 反欺诈待复核操作日志 | G110: 0
A111: db_nono | B111: black_gray_list | C111: 反欺诈黑灰名单库,用于存储欺诈 逾期 失信的用户 | D111: 35361 | E111: 42592.771 | F111: 反欺诈黑灰名单库,用于存储欺诈 逾期 失信的用户 | G111: -957
A112: db_nono | B112: black_gray_rule | D112: 45 | E112: 42592.771 | G112: 0
A113: db_nono | B113: blacklist | C113: 黑名单 | D113: 13039 | E113: 42156.144 | F113: 黑名单 | G113: 0
A114: db_nono | B114: blb_province_threshold | C114: 白领包省市阀值表 | D114: 33 | E114: 42184.896 | F114: 白领包省市阀值表 | G114: 0
A115: db_nono | B115: blb_student_school | C115: 白领包学校信息表 | D115: 1257 | E115: 42184.896 | F115: 白领包学校信息表 | G115: -1
A116: db_nono | B116: bonus_template | D116: 3 | E116: 42600.421 | G116: 0
A117: db_nono | B117: borrows | C117: 借款表 | D117: 1322275 | E117: 42080.382 | F117: 借款表 | G117: -5004
A118: db_nono | B118: borrows_accept | C118: 借出者收款表 | D118: 221366105 | E118: 42080.382 | F118: 借出者收款表 | G118: -7896950
A119: db_nono | B119: borrows_accept_delta | C119: 借出者收款表 | D119: 0 | E119: 42612.412 | F119: 借出者收款表 | G119: 0
A120: db_nono | B120: borrows_accept_log | C120: 借出者收款表日志表，保存ba版本快照 | D120: 252329 | E120: 42614.701 | F120: 借出者收款表日志表，保存ba版本快照 | G120: 1243
A121: db_nono | B121: borrows_agreement | C121: 借款协议数据表 | D121: 15899 | E121: 42654.7 | F121: 借款协议数据表 | G121: 2122
A122: db_nono | B122: borrows_archive | C122: 认证表 | D122: 908477 | E122: 42080.382 | F122: 借款存档表（担保、视频认证） | G122: -23867
A123: db_nono | B123: borrows_autobidder | C123: 散投自动投标器表 | D123: 2900 | E123: 42156.16 | F123: 散投自动投标器表 | G123: -2
A124: db_nono | B124: borrows_bidding | C124: 投标表 | D124: 5662858 | E124: 42080.382 | F124: 散投投资订单表 | G124: -182420
A125: db_nono | B125: borrows_collateral_attaches | C125: 抵押物附件表 原表collateral_attaches | D125: 126 | E125: 42156.161 | F125: 抵押物附件表 原表collateral_attaches | G125: 0
A126: db_nono | B126: borrows_collateral_detail | C126: 抵押物详情表 原表collateral_detail | D126: 23 | E126: 42156.161 | F126: 抵押物详情表 原表collateral_detail | G126: 0
A127: db_nono | B127: borrows_collateral_status | C127: 抵押物状态表 原表collateral_status | D127: 23 | E127: 42156.161 | F127: 抵押物状态表 原表collateral_status | G127: 0
A128: db_nono | B128: borrows_comment | C128: 借款留言 | D128: 3381 | E128: 42080.382 | F128: 借款留言 | G128: 0
... A142: db_nono | B142: borrows_prepare | C142: 预发标 | D142: 1641261 | E142: 42080.382 | F142: 预借款表 | G142: -38803
A143: db_nono | B143: borrows_prepare_audit | D143: 7331 | E143: 42156.162 | G143: -13
A144: db_nono | B144: borrows_prepare_audit_info | D144: 532 | E144: 42080.382 | G144: 0
...

Sheet 业务流程 (2)
A4: 验证 | B4: 注册 | C4: 认证 | D4: 登录 | E4: 充值 | F4: 投资产品 | G4: 投资订单 | H4: 账户 | I4: 投资兑付 | J4: 提现 | K4: 券 | L4: 活动 | M4: 维表
A5: activity_mobiles | B5: user_info | C5: pengyuan_recharge_log | D5: user_action_log | E5: bill_recharges | F5: csyy_plan | G5: borrows_bidding | H5: finance_account | I5: vip_account | J5: withdraw_cash | K5: bank_code | L5: activity_vip | M5: america_school
A6: sms_channel_info | B6: user_info_detail | C6: user_bankcard_auth | D6: user_login_info | E6: kuaiq_orders | F6: debt_batch | G6: debt_buy_log | H6: fund_account | I6: fund_redeem_form | J6: withdraw_cash_alipay | K6: coupon_use | L6: activity_vip_label | M6: channel
A7: system_sms_log | B7: user_approach_info | C7: user_bankcard_info | E7: kuaiq_recharge_logs | F7: debt_sale | G7: vip_form | H7: vip_account | I7: borrows_accept | K7: unifi_InterestrateCut | L7: activity_vip_physicalgoods | M7: county_idnum_list
A8: system_voice_verify_log | B8: user_student_info | C8: nono_studentAuth_log | E8: online_recharge | F8: finance_plan | G8: fund_form | H8: finance_log | I8: debt_accept | K8: user_InterestrateCut | L8: activity_vip_physicalgoods_info | M8: region
B9: user_level | C9: nono_authentication | E9: recharge_log | F9: finance_plan_scope | G9: debt_buy_relation_log | H9: finance_operation | K9: user_coupon | L9: activity_vip_praise_log | M9: student_school
B10: user_spouse_info | C10: authentication_htsb | E10: sft_recharges | F10: invt_finance_plan_stage_info | G10: lazy_add | H10: finance_operation_relation | K10: user_hkconpon | L10: activity_vip_virtualgoods | M10: bank_info
B11: user_work_info | C11: borrows_archive | E11: yilian_orders | F11: invt_stage_debt_match | G11: debt_batch_buy_log | H11: finance_role | K11: user_experience_cash_log | L11: activity_point_log | M11: admin
B12: newborn_student_info | C12: mxd_score_result | E12: yilian_recharges | F12: invt_stage_debt_package | K12: user_experience_earnings_log | L12: activity_prize_gain_list
B13: user_company_info | C13: sesame_credit | E13: tb_pay_record | F13: invt_stage_lock_change_log | L13: activity_prize_list
B14: account_relation | C14: user_htsb_info | E14: tb_pay_record_log | F14: invt_user_debts_changes_log
C15: user_credit_investigation
C16: user_credit_rating_info
C17: face_beyond_result
C18: credit_user_htsb_info
F19: 贷款产品 | G19: 贷款订单 | I19: 贷后
F20: products | G20: borrows_loan | I20: borrows_outsource_dunning
F21: bill | G21: borrows_prepare | I21: black_gray_list
F22: bill_repayment_history | G22: borrows | I22: black_gray_rule
F23: credit_account | G23: borrows_consulted_fee
F24: credit_consume_log
G26: user_csmFinInfo
G27: borrows
G28: products
G29: borrows_guarantee
G30: borrows_repayment
G31: borrows_dunning_contact
G32: borrows_loan
G33: admin_work_remark
G34: borrows_raise
G35: borrows_prepare
G36: borrows_consulted_fee

Sheet 数据表
A1: 数据库 | B1: 流程 | C1: 表名 | D1: 表格描述 | E1: 行数 | F1: 创建时间 | G1: 人工备注 | H1: 新增行数
A2: db_nono | C2: InterestrateCut_template | D2: 减息券的模板 | E2: 62 | F2: 42315.694 | G2: 减息券的模板 | H2: -1
A3: db_nono | C3: MGT_RESOURCE | E3: 16 | F3: 42185.931 | H3: 0
A4: db_nono | C4: MGT_ROLE | E4: 3 | F4: 42185.931 | H4: 0
A5: db_nono | C5: MGT_ROLE_RESOURCE | E5: 9 | F5: 42185.931 | H5: 0
A6: db_nono | C6: MGT_USER | E6: 85 | F6: 42185.931 | H6: 0
A7: db_nono | C7: MGT_USER_ROLE | E7: 15 | F7: 42185.931 | H7: 0
A8: db_nono | C8: QRTZ_CRON_TRIGGERS | E8: 6 | F8: 42185.932 | H8: 0
A9: db_nono | C9: QRTZ_FIRED_TRIGGERS | E9: 1 | F9: 42185.932 | H9: 1
A10: db_nono | C10: QRTZ_JOB_DETAILS | E10: 6 | F10: 42185.932 | H10: 0
A11: db_nono | C11: QRTZ_LOCKS | E11: 2 | F11: 42185.932 | H11: 0
A12: db_nono | C12: QRTZ_SCHEDULER_STATE | E12: 1 | F12: 42185.932 | H12: 0
A13: db_nono | C13: QRTZ_TRIGGERS | E13: 6 | F13: 42185.932 | H13: 0
A14: db_nono | C14: SCHEDULE_JOB | E14: 6 | F14: 42185.932 | H14: 0
A15: db_nono | C15: WeiXin_Qr_Code | D15: 微信二维码 | E15: 32 | F15: 42174.735 | G15: 微信二维码 | H15: 0
A16: db_nono | B16: 0元付 | C16: bill | D16: 账单表，计算所有人的账单 | E16: 43737 | F16: 42169.413 | G16: 账单表，计算所有人的账单 | H16: 0
A17: db_nono | C17: action_log | D17: 操作日志表 | E17: 619046 | F17: 42247.784 | G17: 操作日志表 | H17: -567
A18: db_nono | C18: activity | D18: 活动表 | E18: 10 | F18: 42080.382 | G18: 活动表 | H18: 0
A19: db_nono | C19: activity_access_log | D19: 活动日志表 | E19: 3646 | F19: 42080.382 | G19: 财运活动表 | H19: 0
A20: db_nono | C20: activity_begging | E20: 31100 | F20: 42140.414 | H20: 0
A21: db_nono | C21: activity_begging_details | E21: 39828 | F21: 42140.415 | H21: 0
A22: db_nono | C22: activity_goods | D22: 活动商品表 | E22: 8 | F22: 42502.66 | G22: 活动商品表 | H22: 0
A23: db_nono | C23: activity_goods_log | D23: 商品库存修改记录表 | E23: 9 | F23: 42502.66 | G23: 商品库存修改记录表 | H23: 0
A24: db_nono | C24: activity_interest | D24: 活动收益表 | E24: 693 | F24: 42080.382 | G24: 大房东加息结果 | H24: 0
A25: db_nono | C25: activity_interest_details | D25: 活动收益详细信息表 | E25: 4042 | F25: 42080.382 | G25: 大房东加息详情 | H25: 0
A26: db_nono | C26: activity_messages | D26: 活动消息表 | E26: 6019711 | F26: 42080.382 | G26: 每月精选收益短信发送记录 | H26: -113314
A27: db_nono | B27: 0元付 | C27: bill_repayment_history | D27: 账单还款记录表，每还一次款会在这里生成一条记录 | E27: 7408 | F27: 42169.413 | G27: 账单还款记录表，每还一次款会在这里生成一条记录 | H27: -16
A28: db_nono | C28: activity_nbparty_user_info | E28: 41625 | F28: 42527.806 | H28: 0
A29: db_nono | B29: 0元付 | C29: credit_account | D29: 信用账户表 | E29: 8028 | F29: 42169.413 | G29: 信用账户表 | H29: -39
A30: db_nono | C30: activity_point_log_back | E30: 32817272 | F30: 42499.666 | H30: 0
A31: db_nono | B31: 0元付 | C31: credit_consume_log | D31: 信用消费记录表 | E31: 149255 | F31: 42169.413 | G31: 信用消费记录表 | H31: -147
A32: db_nono | C32: activity_prize_gain_list_back | E32: 27192697 | F32: 42499.686 | H32: 0
A33: db_nono | B33: 镑客大使邀请 | C33: activity_prolocutor | D33: 镑客大使表(原表名prolocutor) | E33: 409479 | F33: 42156.142 | G33: 镑客大使表(原表名prolocutor) | H33: -1326
A34: db_nono | B34: 充值 | C34: bill_recharges | D34: 快钱充值流水记录表 | E34: 183312 | F34: 42080.382 | G34: 快钱充值流水记录表 | H34: 0
A35: db_nono | C35: activity_prolocutor_code | E35: 274209 | F35: 42192.655 | H35: -965
A36: db_nono | C36: activity_red_packet | D36: 红包记录表 | E36: 66160 | F36: 42395.776 | G36: 红包记录表 | H36: 0
A37: db_nono | C37: activity_red_packet_gain_log | D37: 红包领取记录表 | E37: 968142 | F37: 42395.776 | G37: 红包领取记录表 | H37: 0
A38: db_nono | C38: activity_red_packet_resend_log | D38: 红包复发记录表 | E38: 37037 | F38: 42395.776 | G38: 红包复发记录表 | H38: 0
A39: db_nono | C39: activity_redrain | D39: 红包雨表 | E39: 3670 | F39: 42097.771 | G39: 客户获取红包总表 | H39: 0
A40: db_nono | C40: activity_redrain_details | D40: 红包雨详细信息表 | E40: 3639 | F40: 42097.771 | G40: 客户获取红包详情表 | H40: 0
A41: db_nono | C41: activity_redrain_mobiles | D41: qq红包活动用户手机号记录(原表名qq_activity_mobiles) | E41: 152 | F41: 42156.142 | G41: qq红包活动用户手机号记录(原表名qq_activity_mobiles) | H41: 0
A42: db_nono | C42: activity_seven_years_account | D42: 7周年活动用户账单表 | E42: 151945 | F42: 42523.413 | G42: 7周年活动用户账单表 | H42: 0
A43: db_nono | C43: activity_seven_years_percent_line | D43: 七周年用户投资百分比达标线 | E43: 553898 | F43: 42523.413 | G43: 七周年用户投资百分比达标线 | H43: -15437
A44: db_nono | C44: activity_statistic | D44: 活动统计表 | E44: 97935 | F44: 42080.382 | G44: 客户推荐链接点击客户ip信息 | H44: 0
A45: db_nono | C45: activity_user_goods | D45: 用户领取活动商品表 | E45: 6 | F45: 42502.66 | G45: 用户领取活动商品表 | H45: 0
A46: db_nono | B46: 充值 | C46: kuaiq_orders | D46: 快钱订单表 | E46: 12030794 | F46: 42080.382 | G46: 快钱充值订单 | H46: -184731
A47: db_nono | B47: 充值 | C47: kuaiq_recharge_logs | D47: 快钱操作记录流水表 | E47: 33851963 | F47: 42080.382 | G47: 快钱充值日志及备注 | H47: -668575
A48: db_nono | B48: 充值 | C48: online_recharge | D48: 在线充值 对应原数据库recharge_online | E48: 1010980 | F48: 42156.182 | G48: 在线充值 对应原数据库recharge_online | H48: -10590
A49: db_nono | B49: 充值 | C49: recharge_log | D49: 充值记录表 | E49: 3405208 | F49: 42187.777 | G49: 充值记录表 | H49: -36696
A50: db_nono | B50: 充值 | C50: sft_recharges | D50: 盛付通充值流水记录表 | E50: 366354 | F50: 42080.382 | G50: 盛付通充值流水记录表 | H50: -88
A51: db_nono | C51: activity_vip_service | D51: 超镑服务表原表名：chaobang_service | E51: 2 | F51: 42156.142 | G51: 超镑服务表原表名：chaobang_service | H51: 0
A52: db_nono | C52: activity_vip_service_info | D52: 超镑服务详情表原表名：chaobang_service_info | E52: 1 | F52: 42156.142 | G52: 超镑服务详情表原表名：chaobang_service_info | H52: 0
A53: db_nono | B53: 充值 | C53: yilian_orders | D53: 易联订单表 | E53: 609908 | F53: 42080.383 | G53: 易联订单 | H53: -6047
A54: db_nono | C54: activity_wdybm_info | D54: 微电影报名活动表 | E54: 54 | F54: 42185.769 | G54: 微电影报名活动表 | H54: 0
A55: db_nono | C55: activity_youmi | D55: 优米(原表名youmi_logyoumi) | E55: 4936 | F55: 42156.142 | G55: 优米(原表名youmi_logyoumi) | H55: 0
A56: db_nono | C56: activity_youmi_action | D56: 优米行为(原表名youmi_logyoumi_action) | E56: 7 | F56: 42156.142 | G56: 优米行为(原表名youmi_logyoumi_action) | H56: 0
A57: db_nono | C57: activity_youmi_log | D57: 优米日志表(原表名youmi_log) | E57: 4859 | F57: 42156.142 | G57: 优米日志表(原表名youmi_log) | H57: 0
A58: db_nono | B58: 充值 | C58: yilian_recharges | D58: 易联操作记录表 | E58: 541225 | F58: 42080.383 | G58: 易联操作记录表 | H58: -6581
A59: db_nono | C59: admin_action_log | D59: 登录记录表 | E59: 312257 | F59: 42080.382 | G59: 后台管理及渠道id登陆日志 | H59: -2606
A60: db_nono | C60: admin_advisor_conf | D60: 财富顾问关联用户限制表(原表名members_caifu) | E60: 179 | F60: 42156.142 | G60: 财富顾问关联用户限制表(原表名members_caifu) | H60: 0
A61: db_nono | C61: admin_calendar | D61: 员工排班表 | E61: 3450 | F61: 42080.382 | G61: 员工排班表 | H61: -14
A62: db_nono_pay | B62: 充值 | C62: tb_pay_record | E62: 3252907 | F62: 42502.479 | H62: -64938
A63: db_nono | C63: admin_ip_blacklist | D63: 禁用IP列表 | E63: 17 | F63: 42080.382 | G63: 禁用IP列表 | H63: 0
A64: db_nono | C64: admin_ip_limit | D64: ip限制表 | E64: 20 | F64: 42080.382 | G64: 后台直接登陆IP限制表 | H64: 0
A65: db_nono | C65: admin_menu_modules | D65: 菜单关联表 | E65: 100 | F65: 42080.382 | G65: 菜单关联表 | H65: 1
A66: db_nono | C66: admin_menus | D66: 菜单表 | E66: 230 | F66: 42080.382 | G66: 菜单表 | H66: 1
A67: db_nono | C67: admin_operation | D67: 管理员操作表 | E67: 2434513 | F67: 42080.382 | G67: 管理员操作表 | H67: -38261
A68: db_nono | C68: admin_qa_answers | D68: 问题回答表(原表名answers) | E68: 6 | F68: 42156.142 | G68: 问题回答表(原表名answers) | H68: 0
A69: db_nono | C69: admin_qa_questions | D69: 问题表(原表名questions) | E69: 220 | F69: 42156.142 | G69: 问题表(原表名questions) | H69: 0
A70: db_nono | C70: admin_role | D70: 角色表 | E70: 158 | F70: 42080.382 | G70: 角色表 | H70: -2
A71: db_nono_pay | B71: 充值 | C71: tb_pay_record_log | E71: 14952861 | F71: 42475.553 | H71: -397326
A72: db_nono | B72: 贷后催收 | C72: borrows_outsource_dunning | D72: 会员委外催收 原表members_outsource_dunning | E72: 316309 | F72: 42156.162 | G72: 会员委外催收 原表members_outsource_dunning | H72: 0
A73: db_nono | B73: 贷后黑名单 | C73: black_gray_list | D73: 反欺诈黑灰名单库,用于存储欺诈 逾期 失信的用户 | E73: 35361 | F73: 42592.771 | G73: 反欺诈黑灰名单库,用于存储欺诈 逾期 失信的用户 | H73: -957
A74: db_nono | C74: analyse_calendar | E74: 34 | F74: 42191.591 | H74: 0
A75: db_nono | C75: analyse_licai | E75: 378 | F75: 42191.583 | H75: 0
A76: db_nono | C76: app_pic | D76: app 图片表 | E76: 105 | F76: 42303.623 | G76: app 图片表 | H76: -6
A77: db_nono | C77: app_system | D77: app设备记录表 | E77: 1812 | F77: 42080.382 | G77: app设备记录表 | H77: 0
A78: db_nono | C78: app_upload_files | D78: app附件上传记录表 | E78: 1675603 | F78: 42080.685 | G78: 客户app上传资料 | H78: -18255
A79: db_nono | C79: app_visit_record | D79: app设备访问记录表 | E79: 2790 | F79: 42080.382 | G79: app设备访问记录表 | H79: 0
A80: db_nono | C80: articles | D80: 资讯表 | E80: 1597 | F80: 42080.382 | G80: 文章表 | H80: -21
A81: db_nono | C81: articles_cat | D81: 资讯分类表 | E81: 42 | F81: 42080.382 | G81: 资讯分类表 | H81: 0
A82: db_nono | C82: authen_author_log | D82: 开通鉴权表 | E82: 2076156 | F82: 42187.777 | G82: 开通鉴权表 | H82: -31444
A83: db_nono | B83: 贷后黑名单 | C83: black_gray_rule | E83: 45 | F83: 42592.771 | H83: 0
A84: db_nono | C84: authentication_htsb_log | D84: 活体识别日志表(原表名htsb_log) | E84: 713066 | F84: 42156.143 | G84: 活体识别日志表(原表名htsb_log) | H84: -36947
A85: db_nono | C85: autobid_log | D85: 精选&散投自动投标日志表 | E85: 5524722 | F85: 42080.382 | G85: 自动投标日志表 | H85: -111081
A86: db_nono | C86: ba_trigger_delta | E86: 18677820 | F86: 42609.929 | H86: -471693
A87: db_nono | C87: bank | D87: 银行省份关联表 | E87: 93536 | F87: 42156.144 | G87: 银行省份关联表 | H87: 0
A88: db_nono | C88: bank_card_info | D88: 银行卡信息表(原表名bank_info) | E88: 2144 | F88: 42156.144 | G88: 银行卡信息表(原表名bank_info) | H88: 0
A89: db_nono | B89: 贷款 | C89: user_csmFinInfo | D89: 用户对用的消费金融信息表 | E89: 7474 | F89: 42545.749 | G89: 用户对用的消费金融信息表 | H89: 6
A90: db_nono | C90: bank_code_relation | E90: 25 | F90: 42326.969 | H90: 0
A91: db_nono | B91: 贷款表 | C91: borrows | D91: 借款表 | E91: 1322275 | F91: 42080.382 | G91: 借款表 | H91: -5004
A92: db_nono | C92: bank_payment_warning | E92: 55 | F92: 42160.587 | H92: 0
A93: db_nono | B93: 贷款产品 | C93: products | D93: 产品表 | E93: 94 | F93: 42080.382 | G93: 产品描述 | H93: -1
A94: db_nono | B94: 贷款代偿 | C94: borrows_guarantee | D94: 借入者代偿表 | E94: 833036 | F94: 42080.382 | G94: 担保人担保存款列表 | H94: -20496
A95: db_nono | B95: 贷款还款表 | C95: borrows_repayment | D95: 借入者还款表 | E95: 12425476 | F95: 42080.382 | G95: 借入者还款表 | H95: -213005
A96: db_nono | C96: bill_wechat_pre | D96: 0元付账单微信二维码预支付参数表 | E96: 2103903 | F96: 42312.676 | G96: 0元付账单微信二维码预支付参数表 | H96: -55443
A97: db_nono | C97: bkds_temporary | E97: 25 | F97: 42416.869 | H97: 0
A98: db_nono | B98: 贷款联系人 | C98: borrows_dunning_contact | D98: 会员联系人表 原表members_dunning_contact | E98: 5435360 | F98: 42156.161 | G98: 会员联系人表 原表members_dunning_contact | H98: -73988
A99: db_nono | B99: 贷款申请进件 | C99: borrows_loan | D99: 进件 old table:members_loan | E99: 1193588 | F99: 42156.162 | G99: 进件 old table:members_loan | H99: -26913
A100: db_nono | C100: blacklist | D100: 黑名单 | E100: 13039 | F100: 42156.144 | G100: 黑名单 | H100: 0
...

Sheet 业务流程
A1: 诺诺、名校贷、大房东、unifi | C1: 财神爷爷 | E1: 麦芽分期 | G1: 诺诺、名校贷、大房东、unifi
A2: 类别/表名 | B2: 表描述 | C2: 类别/表名 | D2: 表描述 | E2: 类别/表名 | F2: 表描述 | G2: 类别/表名 | H2: 表描述
A3: 验证 | G3: 维表
A4: activity_mobiles | B4: =LEFT(IFERROR(VLOOKUP(A4,数据表!C:D,2,0),""),10) -> 活动手机号表 | D4: =LEFT(IFERROR(VLOOKUP(C4,数据表!C:D,2,0),""),10) | F4: =LEFT(IFERROR(VLOOKUP(E4,数据表!C:D,2,0),""),10) | G4: america_school | H4: =LEFT(IFERROR(VLOOKUP(G4,数据表!C:D,2,0),""),10) -> 美国学校信息表
A5: sms_channel_info | B5: =LEFT(IFERROR(VLOOKUP(A5,数据表!C:D,2,0),""),10) | D5: =LEFT(IFERROR(VLOOKUP(C5,数据表!C:D,2,0),""),10) | F5: =LEFT(IFERROR(VLOOKUP(E5,数据表!C:D,2,0),""),10) | G5: channel | H5: =LEFT(IFERROR(VLOOKUP(G5,数据表!C:D,2,0),""),10) -> 渠道表
A6: system_sms_log | B6: =LEFT(IFERROR(VLOOKUP(A6,数据表!C:D,2,0),""),10) -> 短信发送日志表 | D6: =LEFT(IFERROR(VLOOKUP(C6,数据表!C:D,2,0),""),10) | F6: =LEFT(IFERROR(VLOOKUP(E6,数据表!C:D,2,0),""),10) | G6: county_idnum_list | H6: =LEFT(IFERROR(VLOOKUP(G6,数据表!C:D,2,0),""),10) -> 区域身份证号码表
A7: system_voice_verify_log | B7: =LEFT(IFERROR(VLOOKUP(A7,数据表!C:D,2,0),""),10) -> 语音校验日志 | D7: =LEFT(IFERROR(VLOOKUP(C7,数据表!C:D,2,0),""),10) | F7: =LEFT(IFERROR(VLOOKUP(E7,数据表!C:D,2,0),""),10) | G7: region | H7: =LEFT(IFERROR(VLOOKUP(G7,数据表!C:D,2,0),""),10) -> 行政区划
B8: =LEFT(IFERROR(VLOOKUP(A8,数据表!C:D,2,0),""),10) | D8: =LEFT(IFERROR(VLOOKUP(C8,数据表!C:D,2,0),""),10) | F8: =LEFT(IFERROR(VLOOKUP(E8,数据表!C:D,2,0),""),10) | G8: student_school | H8: =LEFT(IFERROR(VLOOKUP(G8,数据表!C:D,2,0),""),10) -> 学校信息表
A9: 注册 | B9: =LEFT(IFERROR(VLOOKUP(A9,数据表!C:D,2,0),""),10) | D9: =LEFT(IFERROR(VLOOKUP(C9,数据表!C:D,2,0),""),10) | F9: =LEFT(IFERROR(VLOOKUP(E9,数据表!C:D,2,0),""),10) | G9: bank_info | H9: =LEFT(IFERROR(VLOOKUP(G9,数据表!C:D,2,0),""),10) -> 银行信息表(原表名b
A10: user_info | B10: =LEFT(IFERROR(VLOOKUP(A10,数据表!C:D,2,0),""),10) -> 用户基本信息 | C10: user | D10: =LEFT(IFERROR(VLOOKUP(C10,数据表!C:D,2,0),""),10) -> 会员信息表 | E10: ORD_USER | F10: =LEFT(IFERROR(VLOOKUP(E10,数据表!C:D,2,0),""),10) -> 借款用户基本信息表 | G10: admin | H10: =LEFT(IFERROR(VLOOKUP(G10,数据表!C:D,2,0),""),10) -> 管理员表
A11: user_info_detail | B11: =LEFT(IFERROR(VLOOKUP(A11,数据表!C:D,2,0),""),10) -> 用户详细信息 | C11: user_detail | D11: =LEFT(IFERROR(VLOOKUP(C11,数据表!C:D,2,0),""),10) -> 用户明细信息表 | E11: ORD_USER_DETAIL | F11: =LEFT(IFERROR(VLOOKUP(E11,数据表!C:D,2,0),""),10) -> 用户详情表 | H11: =LEFT(IFERROR(VLOOKUP(G11,数据表!C:D,2,0),""),10)
A12: user_approach_info | B12: =LEFT(IFERROR(VLOOKUP(A12,数据表!C:D,2,0),""),10) -> 用户渠道信息表 | C12: user_approach | D12: =LEFT(IFERROR(VLOOKUP(C12,数据表!C:D,2,0),""),10) | F12: =LEFT(IFERROR(VLOOKUP(E12,数据表!C:D,2,0),""),10) | H12: =LEFT(IFERROR(VLOOKUP(G12,数据表!C:D,2,0),""),10)
A13: user_student_info | B13: =LEFT(IFERROR(VLOOKUP(A13,数据表!C:D,2,0),""),10) -> 学生信息 | C13: user_relation | D13: =LEFT(IFERROR(VLOOKUP(C13,数据表!C:D,2,0),""),10) | F13: =LEFT(IFERROR(VLOOKUP(E13,数据表!C:D,2,0),""),10) | H13: =LEFT(IFERROR(VLOOKUP(G13,数据表!C:D,2,0),""),10)
A14: user_level | B14: =LEFT(IFERROR(VLOOKUP(A14,数据表!C:D,2,0),""),10) -> 会员等级表 | D14: =LEFT(IFERROR(VLOOKUP(C14,数据表!C:D,2,0),""),10) | F14: =LEFT(IFERROR(VLOOKUP(E14,数据表!C:D,2,0),""),10) | H14: =LEFT(IFERROR(VLOOKUP(G14,数据表!C:D,2,0),""),10)
A15: user_spouse_info | B15: =LEFT(IFERROR(VLOOKUP(A15,数据表!C:D,2,0),""),10) -> 用户配偶信息 | D15: =LEFT(IFERROR(VLOOKUP(C15,数据表!C:D,2,0),""),10) | F15: =LEFT(IFERROR(VLOOKUP(E15,数据表!C:D,2,0),""),10) | H15: =LEFT(IFERROR(VLOOKUP(G15,数据表!C:D,2,0),""),10)
A16: user_work_info | B16: =LEFT(IFERROR(VLOOKUP(A16,数据表!C:D,2,0),""),10) -> 用户工作信息 | D16: =LEFT(IFERROR(VLOOKUP(C16,数据表!C:D,2,0),""),10) | F16: =LEFT(IFERROR(VLOOKUP(E16,数据表!C:D,2,0),""),10) | H16: =LEFT(IFERROR(VLOOKUP(G16,数据表!C:D,2,0),""),10)
A17: newborn_student_info | B17: =LEFT(IFERROR(VLOOKUP(A17,数据表!C:D,2,0),""),10) | D17: =LEFT(IFERROR(VLOOKUP(C17,数据表!C:D,2,0),""),10) | F17: =LEFT(IFERROR(VLOOKUP(E17,数据表!C:D,2,0),""),10) | H17: =LEFT(IFERROR(VLOOKUP(G17,数据表!C:D,2,0),""),10)
A18: user_company_info | B18: =LEFT(IFERROR(VLOOKUP(A18,数据表!C:D,2,0),""),10) -> 用户公司信息表 | D18: =LEFT(IFERROR(VLOOKUP(C18,数据表!C:D,2,0),""),10) | F18: =LEFT(IFERROR(VLOOKUP(E18,数据表!C:D,2,0),""),10) | H18: =LEFT(IFERROR(VLOOKUP(G18,数据表!C:D,2,0),""),10)
A19: account_relation | B19: =LEFT(IFERROR(VLOOKUP(A19,数据表!C:D,2,0),""),10) | D19: =LEFT(IFERROR(VLOOKUP(C19,数据表!C:D,2,0),""),10) | F19: =LEFT(IFERROR(VLOOKUP(E19,数据表!C:D,2,0),""),10) | H19: =LEFT(IFERROR(VLOOKUP(G19,数据表!C:D,2,0),""),10)
B20: =LEFT(IFERROR(VLOOKUP(A20,数据表!C:D,2,0),""),10) | D20: =LEFT(IFERROR(VLOOKUP(C20,数据表!C:D,2,0),""),10) | F20: =LEFT(IFERROR(VLOOKUP(E20,数据表!C:D,2,0),""),10) | H20: =LEFT(IFERROR(VLOOKUP(G20,数据表!C:D,2,0),""),10)
A21: 认证 | B21: =LEFT(IFERROR(VLOOKUP(A21,数据表!C:D,2,0),""),10) | D21: =LEFT(IFERROR(VLOOKUP(C21,数据表!C:D,2,0),""),10) | F21: =LEFT(IFERROR(VLOOKUP(E21,数据表!C:D,2,0),""),10) | H21: =LEFT(IFERROR(VLOOKUP(G21,数据表!C:D,2,0),""),10)
A22: pengyuan_recharge_log | B22: =LEFT(IFERROR(VLOOKUP(A22,数据表!C:D,2,0),""),10) -> 鹏元认证日志表 | C22: authen_log | D22: =LEFT(IFERROR(VLOOKUP(C22,数据表!C:D,2,0),""),10) -> 调用第三方认证日志记 | F22: =LEFT(IFERROR(VLOOKUP(E22,数据表!C:D,2,0),""),10) | H22: =LEFT(IFERROR(VLOOKUP(G22,数据表!C:D,2,0),""),10)
A23: user_bankcard_auth | B23: =LEFT(IFERROR(VLOOKUP(A23,数据表!C:D,2,0),""),10) -> 银行卡鉴权信息表 | C23: user_bind_card | D23: =LEFT(IFERROR(VLOOKUP(C23,数据表!C:D,2,0),""),10) -> 绑定银行卡信息 | F23: =LEFT(IFERROR(VLOOKUP(E23,数据表!C:D,2,0),""),10) | H23: =LEFT(IFERROR(VLOOKUP(G23,数据表!C:D,2,0),""),10)
A24: user_bankcard_info | B24: =LEFT(IFERROR(VLOOKUP(A24,数据表!C:D,2,0),""),10) -> 银行卡信息表，原表名 | D24: =LEFT(IFERROR(VLOOKUP(C24,数据表!C:D,2,0),""),10) | F24: =LEFT(IFERROR(VLOOKUP(E24,数据表!C:D,2,0),""),10) | H24: =LEFT(IFERROR(VLOOKUP(G24,数据表!C:D,2,0),""),10)
A25: nono_studentAuth_log | B25: =LEFT(IFERROR(VLOOKUP(A25,数据表!C:D,2,0),""),10) -> 学生学籍认证历史信息 | D25: =LEFT(IFERROR(VLOOKUP(C25,数据表!C:D,2,0),""),10) | F25: =LEFT(IFERROR(VLOOKUP(E25,数据表!C:D,2,0),""),10) | H25: =LEFT(IFERROR(VLOOKUP(G25,数据表!C:D,2,0),""),10)
A26: nono_authentication | B26: =LEFT(IFERROR(VLOOKUP(A26,数据表!C:D,2,0),""),10) -> nono认证库表 | D26: =LEFT(IFERROR(VLOOKUP(C26,数据表!C:D,2,0),""),10) | F26: =LEFT(IFERROR(VLOOKUP(E26,数据表!C:D,2,0),""),10) | H26: =LEFT(IFERROR(VLOOKUP(G26,数据表!C:D,2,0),""),10)
A27: authentication_htsb | B27: =LEFT(IFERROR(VLOOKUP(A27,数据表!C:D,2,0),""),10) -> 活体识别日志表(原表 | D27: =LEFT(IFERROR(VLOOKUP(C27,数据表!C:D,2,0),""),10) | F27: =LEFT(IFERROR(VLOOKUP(E27,数据表!C:D,2,0),""),10) | H27: =LEFT(IFERROR(VLOOKUP(G27,数据表!C:D,2,0),""),10)
A28: borrows_archive | B28: =LEFT(IFERROR(VLOOKUP(A28,数据表!C:D,2,0),""),10) -> 认证表 | D28: =LEFT(IFERROR(VLOOKUP(C28,数据表!C:D,2,0),""),10) | F28: =LEFT(IFERROR(VLOOKUP(E28,数据表!C:D,2,0),""),10) | H28: =LEFT(IFERROR(VLOOKUP(G28,数据表!C:D,2,0),""),10)
A29: mxd_score_result | B29: =LEFT(IFERROR(VLOOKUP(A29,数据表!C:D,2,0),""),10) -> 名校贷评分信息表 | D29: =LEFT(IFERROR(VLOOKUP(C29,数据表!C:D,2,0),""),10) | F29: =LEFT(IFERROR(VLOOKUP(E29,数据表!C:D,2,0),""),10) | H29: =LEFT(IFERROR(VLOOKUP(G29,数据表!C:D,2,0),""),10)
A30: sesame_credit | B30: =LEFT(IFERROR(VLOOKUP(A30,数据表!C:D,2,0),""),10) -> 芝麻信用表，存放所有 | D30: =LEFT(IFERROR(VLOOKUP(C30,数据表!C:D,2,0),""),10) | E30: ORD_USER_HONOR | F30: =LEFT(IFERROR(VLOOKUP(E30,数据表!C:D,2,0),""),10) -> 用户信用表 | H30: =LEFT(IFERROR(VLOOKUP(G30,数据表!C:D,2,0),""),10)
A31: user_htsb_info | B31: =LEFT(IFERROR(VLOOKUP(A31,数据表!C:D,2,0),""),10) -> 用户活体识别信息表 | D31: =LEFT(IFERROR(VLOOKUP(C31,数据表!C:D,2,0),""),10) | F31: =LEFT(IFERROR(VLOOKUP(E31,数据表!C:D,2,0),""),10) | H31: =LEFT(IFERROR(VLOOKUP(G31,数据表!C:D,2,0),""),10)
A32: user_credit_investigation | B32: =LEFT(IFERROR(VLOOKUP(A32,数据表!C:D,2,0),""),10) -> 用户征信相关信息 | D32: =LEFT(IFERROR(VLOOKUP(C32,数据表!C:D,2,0),""),10) | F32: =LEFT(IFERROR(VLOOKUP(E32,数据表!C:D,2,0),""),10) | H32: =LEFT(IFERROR(VLOOKUP(G32,数据表!C:D,2,0),""),10)
A33: user_credit_rating_info | B33: =LEFT(IFERROR(VLOOKUP(A33,数据表!C:D,2,0),""),10) -> 用户信用证书申请 | D33: =LEFT(IFERROR(VLOOKUP(C33,数据表!C:D,2,0),""),10) | F33: =LEFT(IFERROR(VLOOKUP(E33,数据表!C:D,2,0),""),10) | H33: =LEFT(IFERROR(VLOOKUP(G33,数据表!C:D,2,0),""),10)
A34: face_beyond_result | B34: =LEFT(IFERROR(VLOOKUP(A34,数据表!C:D,2,0),""),10) -> 脸部识别，比较结果 | D34: =LEFT(IFERROR(VLOOKUP(C34,数据表!C:D,2,0),""),10) | F34: =LEFT(IFERROR(VLOOKUP(E34,数据表!C:D,2,0),""),10) | H34: =LEFT(IFERROR(VLOOKUP(G34,数据表!C:D,2,0),""),10)
A35: credit_user_htsb_info | B35: =LEFT(IFERROR(VLOOKUP(A35,数据表!C:D,2,0),""),10) -> 用户活体识别信息产品 | D35: =LEFT(IFERROR(VLOOKUP(C35,数据表!C:D,2,0),""),10) | F35: =LEFT(IFERROR(VLOOKUP(E35,数据表!C:D,2,0),""),10) | H35: =LEFT(IFERROR(VLOOKUP(G35,数据表!C:D,2,0),""),10)
B36: =LEFT(IFERROR(VLOOKUP(A36,数据表!C:D,2,0),""),10) | D36: =LEFT(IFERROR(VLOOKUP(C36,数据表!C:D,2,0),""),10) | F36: =LEFT(IFERROR(VLOOKUP(E36,数据表!C:D,2,0),""),10) | H36: =LEFT(IFERROR(VLOOKUP(G36,数据表!C:D,2,0),""),10)
A37: 登录 | B37: =LEFT(IFERROR(VLOOKUP(A37,数据表!C:D,2,0),""),10) | D37: =LEFT(IFERROR(VLOOKUP(C37,数据表!C:D,2,0),""),10) | F37: =LEFT(IFERROR(VLOOKUP(E37,数据表!C:D,2,0),""),10) | H37: =LEFT(IFERROR(VLOOKUP(G37,数据表!C:D,2,0),""),10)
A38: user_action_log | B38: =LEFT(IFERROR(VLOOKUP(A38,数据表!C:D,2,0),""),10) -> 用户操作记录表 | D38: =LEFT(IFERROR(VLOOKUP(C38,数据表!C:D,2,0),""),10) | F38: =LEFT(IFERROR(VLOOKUP(E38,数据表!C:D,2,0),""),10) | H38: =LEFT(IFERROR(VLOOKUP(G38,数据表!C:D,2,0),""),10)
A39: user_login_info | B39: =LEFT(IFERROR(VLOOKUP(A39,数据表!C:D,2,0),""),10) -> 用户登录信息 | D39: =LEFT(IFERROR(VLOOKUP(C39,数据表!C:D,2,0),""),10) | F39: =LEFT(IFERROR(VLOOKUP(E39,数据表!C:D,2,0),""),10) | H39: =LEFT(IFERROR(VLOOKUP(G39,数据表!C:D,2,0),""),10)
B40: =LEFT(IFERROR(VLOOKUP(A40,数据表!C:D,2,0),""),10) | D40: =LEFT(IFERROR(VLOOKUP(C40,数据表!C:D,2,0),""),10) | F40: =LEFT(IFERROR(VLOOKUP(E40,数据表!C:D,2,0),""),10) | H40: =LEFT(IFERROR(VLOOKUP(G40,数据表!C:D,2,0),""),10)
A41: 充值 | B41: =LEFT(IFERROR(VLOOKUP(A41,数据表!C:D,2,0),""),10) | D41: =LEFT(IFERROR(VLOOKUP(C41,数据表!C:D,2,0),""),10) | F41: =LEFT(IFERROR(VLOOKUP(E41,数据表!C:D,2,0),""),10) | H41: =LEFT(IFERROR(VLOOKUP(G41,数据表!C:D,2,0),""),10)
A42: bill_recharges | B42: =LEFT(IFERROR(VLOOKUP(A42,数据表!C:D,2,0),""),10) -> 快钱充值流水记录表 | C42: third_trade_log | D42: =LEFT(IFERROR(VLOOKUP(C42,数据表!C:D,2,0),""),10) -> 第三方平台交易流水记 | F42: =LEFT(IFERROR(VLOOKUP(E42,数据表!C:D,2,0),""),10) | H42: =LEFT(IFERROR(VLOOKUP(G42,数据表!C:D,2,0),""),10)
A43: kuaiq_orders | B43: =LEFT(IFERROR(VLOOKUP(A43,数据表!C:D,2,0),""),10) -> 快钱订单表 | D43: =LEFT(IFERROR(VLOOKUP(C43,数据表!C:D,2,0),""),10) | F43: =LEFT(IFERROR(VLOOKUP(E43,数据表!C:D,2,0),""),10) | H43: =LEFT(IFERROR(VLOOKUP(G43,数据表!C:D,2,0),""),10)
A44: kuaiq_recharge_logs | B44: =LEFT(IFERROR(VLOOKUP(A44,数据表!C:D,2,0),""),10) -> 快钱操作记录流水表 | D44: =LEFT(IFERROR(VLOOKUP(C44,数据表!C:D,2,0),""),10) | F44: =LEFT(IFERROR(VLOOKUP(E44,数据表!C:D,2,0),""),10) | H44: =LEFT(IFERROR(VLOOKUP(G44,数据表!C:D,2,0),""),10)
A45: online_recharge | B45: =LEFT(IFERROR(VLOOKUP(A45,数据表!C:D,2,0),""),10) -> 在线充值 对应原数据 | D45: =LEFT(IFERROR(VLOOKUP(C45,数据表!C:D,2,0),""),10) | F45: =LEFT(IFERROR(VLOOKUP(E45,数据表!C:D,2,0),""),10) | H45: =LEFT(IFERROR(VLOOKUP(G45,数据表!C:D,2,0),""),10)
A46: recharge_log | B46: =LEFT(IFERROR(VLOOKUP(A46,数据表!C:D,2,0),""),10) -> 充值记录表 | D46: =LEFT(IFERROR(VLOOKUP(C46,数据表!C:D,2,0),""),10) | F46: =LEFT(IFERROR(VLOOKUP(E46,数据表!C:D,2,0),""),10) | H46: =LEFT(IFERROR(VLOOKUP(G46,数据表!C:D,2,0),""),10)
A47: sft_recharges | B47: =LEFT(IFERROR(VLOOKUP(A47,数据表!C:D,2,0),""),10) -> 盛付通充值流水记录表 | D47: =LEFT(IFERROR(VLOOKUP(C47,数据表!C:D,2,0),""),10) | F47: =LEFT(IFERROR(VLOOKUP(E47,数据表!C:D,2,0),""),10) | H47: =LEFT(IFERROR(VLOOKUP(G47,数据表!C:D,2,0),""),10)
A48: yilian_orders | B48: =LEFT(IFERROR(VLOOKUP(A48,数据表!C:D,2,0),""),10) -> 易联订单表 | D48: =LEFT(IFERROR(VLOOKUP(C48,数据表!C:D,2,0),""),10) | F48: =LEFT(IFERROR(VLOOKUP(E48,数据表!C:D,2,0),""),10) | H48: =LEFT(IFERROR(VLOOKUP(G48,数据表!C:D,2,0),""),10)
A49: yilian_recharges | B49: =LEFT(IFERROR(VLOOKUP(A49,数据表!C:D,2,0),""),10) -> 易联操作记录表 | D49: =LEFT(IFERROR(VLOOKUP(C49,数据表!C:D,2,0),""),10) | F49: =LEFT(IFERROR(VLOOKUP(E49,数据表!C:D,2,0),""),10) | H49: =LEFT(IFERROR(VLOOKUP(G49,数据表!C:D,2,0),""),10)
A50: tb_pay_record | B50: =LEFT(IFERROR(VLOOKUP(A50,数据表!C:D,2,0),""),10) | D50: =LEFT(IFERROR(VLOOKUP(C50,数据表!C:D,2,0),""),10) | F50: =LEFT(IFERROR(VLOOKUP(E50,数据表!C:D,2,0),""),10) | H50: =LEFT(IFERROR(VLOOKUP(G50,数据表!C:D,2,0),""),10)
A51: tb_pay_record_log | B51: =LEFT(IFERROR(VLOOKUP(A51,数据表!C:D,2,0),""),10) | D51: =LEFT(IFERROR(VLOOKUP(C51,数据表!C:D,2,0),""),10) | F51: =LEFT(IFERROR(VLOOKUP(E51,数据表!C:D,2,0),""),10) | H51: =LEFT(IFERROR(VLOOKUP(G51,数据表!C:D,2,0),""),10)
A52: DW_Nono_Recharge | B52: =LEFT(IFERROR(VLOOKUP(A52,数据表!C:D,2,0),""),10) | D52: =LEFT(IFERROR(VLOOKUP(C52,数据表!C:D,2,0),""),10) | F52: =LEFT(IFERROR(VLOOKUP(E52,数据表!C:D,2,0),""),10) | H52: =LEFT(IFERROR(VLOOKUP(G52,数据表!C:D,2,0),""),10)
A53: DW_Nono_Recharge_Finance | B53: =LEFT(IFERROR(VLOOKUP(A53,数据表!C:D,2,0),""),10) | D53: =LEFT(IFERROR(VLOOKUP(C53,数据表!C:D,2,0),""),10) | F53: =LEFT(IFERROR(VLOOKUP(E53,数据表!C:D,2,0),""),10) | H53: =LEFT(IFERROR(VLOOKUP(G53,数据表!C:D,2,0),""),10)
B54: =LEFT(IFERROR(VLOOKUP(A54,数据表!C:D,2,0),""),10) | D54: =LEFT(IFERROR(VLOOKUP(C54,数据表!C:D,2,0),""),10) | F54: =LEFT(IFERROR(VLOOKUP(E54,数据表!C:D,2,0),""),10) | H54: =LEFT(IFERROR(VLOOKUP(G54,数据表!C:D,2,0),""),10)
A55: 投资产品 | B55: =LEFT(IFERROR(VLOOKUP(A55,数据表!C:D,2,0),""),10) | D55: =LEFT(IFERROR(VLOOKUP(C55,数据表!C:D,2,0),""),10) | F55: =LEFT(IFERROR(VLOOKUP(E55,数据表!C:D,2,0),""),10) | G55: 贷款产品 | H55: =LEFT(IFERROR(VLOOKUP(G55,数据表!C:D,2,0),""),10)
A56: csyy_plan | B56: =LEFT(IFERROR(VLOOKUP(A56,数据表!C:D,2,0),""),10) -> 财神爷爷发布记录表 | C56: debt_detail | D56: =LEFT(IFERROR(VLOOKUP(C56,数据表!C:D,2,0),""),10) -> 产品明细(一个标的下 | E56: SOP_SHOP | F56: =LEFT(IFERROR(VLOOKUP(E56,数据表!C:D,2,0),""),10) -> 商户表 | G56: products | H56: =LEFT(IFERROR(VLOOKUP(G56,数据表!C:D,2,0),""),10) -> 产品表
A57: debt_batch | B57: =LEFT(IFERROR(VLOOKUP(A57,数据表!C:D,2,0),""),10) | C57: product_eff_day | D57: =LEFT(IFERROR(VLOOKUP(C57,数据表!C:D,2,0),""),10) | E57: SOP_SHOP_FACE | F57: =LEFT(IFERROR(VLOOKUP(E57,数据表!C:D,2,0),""),10) -> 商户门店 | G57: bill | H57: =LEFT(IFERROR(VLOOKUP(G57,数据表!C:D,2,0),""),10) -> 账单表，计算所有人的
A58: debt_sale | B58: =LEFT(IFERROR(VLOOKUP(A58,数据表!C:D,2,0),""),10) -> 债权出售表 | C58: product_has_reward | D58: =LEFT(IFERROR(VLOOKUP(C58,数据表!C:D,2,0),""),10) -> 产品奖－励加息配置表 | E58: SOP_SHOP_FACE_RISK | F58: =LEFT(IFERROR(VLOOKUP(E58,数据表!C:D,2,0),""),10) -> 门店风控数据表 | G58: bill_repayment_history | H58: =LEFT(IFERROR(VLOOKUP(G58,数据表!C:D,2,0),""),10) -> 账单还款记录表，每还
A59: finance_plan | B59: =LEFT(IFERROR(VLOOKUP(A59,数据表!C:D,2,0),""),10) -> 诺诺精选表 | C59: product_info | D59: =LEFT(IFERROR(VLOOKUP(C59,数据表!C:D,2,0),""),10) -> 产品信息 | E59: SOP_SHOP_RISK | F59: =LEFT(IFERROR(VLOOKUP(E59,数据表!C:D,2,0),""),10) -> 商户风控信息表 | G59: credit_account | H59: =LEFT(IFERROR(VLOOKUP(G59,数据表!C:D,2,0),""),10) -> 信用账户表
A60: finance_plan_scope | B60: =LEFT(IFERROR(VLOOKUP(A60,数据表!C:D,2,0),""),10) -> 精选类型表 | C60: product_info_detail | D60: =LEFT(IFERROR(VLOOKUP(C60,数据表!C:D,2,0),""),10) | F60: =LEFT(IFERROR(VLOOKUP(E60,数据表!C:D,2,0),""),10) | G60: credit_consume_log | H60: =LEFT(IFERROR(VLOOKUP(G60,数据表!C:D,2,0),""),10) -> 信用消费记录表
A61: invt_finance_plan_stage_info | B61: =LEFT(IFERROR(VLOOKUP(A61,数据表!C:D,2,0),""),10) | C61: product_rate | D61: =LEFT(IFERROR(VLOOKUP(C61,数据表!C:D,2,0),""),10) -> 产品利率 | F61: =LEFT(IFERROR(VLOOKUP(E61,数据表!C:D,2,0),""),10) | H61: =LEFT(IFERROR(VLOOKUP(G61,数据表!C:D,2,0),""),10)
A62: invt_stage_debt_match | B62: =LEFT(IFERROR(VLOOKUP(A62,数据表!C:D,2,0),""),10) -> 精选购买债权预匹配表 | D62: =LEFT(IFERROR(VLOOKUP(C62,数据表!C:D,2,0),""),10) | F62: =LEFT(IFERROR(VLOOKUP(E62,数据表!C:D,2,0),""),10) | G62: 贷款订单 | H62: =LEFT(IFERROR(VLOOKUP(G62,数据表!C:D,2,0),""),10)
A63: invt_stage_debt_package | B63: =LEFT(IFERROR(VLOOKUP(A63,数据表!C:D,2,0),""),10) -> 月月精选每日统一打包 | D63: =LEFT(IFERROR(VLOOKUP(C63,数据表!C:D,2,0),""),10) | E63: ORD_ORDER | F63: =LEFT(IFERROR(VLOOKUP(E63,数据表!C:D,2,0),""),10) -> 订单表 | G63: borrows_loan | H63: =LEFT(IFERROR(VLOOKUP(G63,数据表!C:D,2,0),""),10) -> 进件 old tab
A64: invt_stage_lock_change_log | B64: =LEFT(IFERROR(VLOOKUP(A64,数据表!C:D,2,0),""),10) -> 月月升债权记录和计划 | D64: =LEFT(IFERROR(VLOOKUP(C64,数据表!C:D,2,0),""),10) | F64: =LEFT(IFERROR(VLOOKUP(E64,数据表!C:D,2,0),""),10) | G64: borrows_prepare | H64: =LEFT(IFERROR(VLOOKUP(G64,数据表!C:D,2,0),""),10) -> 预发标
A65: invt_user_debts_changes_log | B65: =LEFT(IFERROR(VLOOKUP(A65,数据表!C:D,2,0),""),10) -> 投资月月升用户债权变 | D65: =LEFT(IFERROR(VLOOKUP(C65,数据表!C:D,2,0),""),10) | F65: =LEFT(IFERROR(VLOOKUP(E65,数据表!C:D,2,0),""),10) | G65: borrows_raise | H65: =LEFT(IFERROR(VLOOKUP(G65,数据表!C:D,2,0),""),10)
B66: =LEFT(IFERROR(VLOOKUP(A66,数据表!C:D,2,0),""),10) | D66: =LEFT(IFERROR(VLOOKUP(C66,数据表!C:D,2,0),""),10) | F66: =LEFT(IFERROR(VLOOKUP(E66,数据表!C:D,2,0),""),10) | G66: borrows_dunning_contact | H66: =LEFT(IFERROR(VLOOKUP(G66,数据表!C:D,2,0),""),10) -> 会员联系人表 原表m
B67: =LEFT(IFERROR(VLOOKUP(A67,数据表!C:D,2,0),""),10) | D67: =LEFT(IFERROR(VLOOKUP(C67,数据表!C:D,2,0),""),10) | F67: =LEFT(IFERROR(VLOOKUP(E67,数据表!C:D,2,0),""),10) | G67: user_csmFinInfo | H67: =LEFT(IFERROR(VLOOKUP(G67,数据表!C:D,2,0),""),10) -> 用户对用的消费金融信
A68: 投资订单 | B68: =LEFT(IFERROR(VLOOKUP(A68,数据表!C:D,2,0),""),10) | D68: =LEFT(IFERROR(VLOOKUP(C68,数据表!C:D,2,0),""),10) | F68: =LEFT(IFERROR(VLOOKUP(E68,数据表!C:D,2,0),""),10) | G68: borrows | H68: =LEFT(IFERROR(VLOOKUP(G68,数据表!C:D,2,0),""),10) -> 借款表
A69: borrows_bidding | B69: =LEFT(IFERROR(VLOOKUP(A69,数据表!C:D,2,0),""),10) -> 投标表 | C69: order_info | D69: =LEFT(IFERROR(VLOOKUP(C69,数据表!C:D,2,0),""),10) -> 回调信息表 | F69: =LEFT(IFERROR(VLOOKUP(E69,数据表!C:D,2,0),""),10) | G69: borrows_archive | H69: =LEFT(IFERROR(VLOOKUP(G69,数据表!C:D,2,0),""),10) -> 认证表
A70: debt_buy_log | B70: =LEFT(IFERROR(VLOOKUP(A70,数据表!C:D,2,0),""),10) -> 债权购买记录表 | C70: trans_detail | D70: =LEFT(IFERROR(VLOOKUP(C70,数据表!C:D,2,0),""),10) -> 交易流水表 | E70: ORD_ORDER_CHECK_HISTORY | F70: =LEFT(IFERROR(VLOOKUP(E70,数据表!C:D,2,0),""),10) -> 订单审核历史表 | G70: admin_work_remark | H70: =LEFT(IFERROR(VLOOKUP(G70,数据表!C:D,2,0),""),10) -> 管理员备注表
A71: vip_form | B71: =LEFT(IFERROR(VLOOKUP(A71,数据表!C:D,2,0),""),10) -> 精选购买表 | C71: user_product | D71: =LEFT(IFERROR(VLOOKUP(C71,数据表!C:D,2,0),""),10) -> 用户成功购买的产品列 | F71: =LEFT(IFERROR(VLOOKUP(E71,数据表!C:D,2,0),""),10) | G71: borrows_consulted_fee | H71: =LEFT(IFERROR(VLOOKUP(G71,数据表!C:D,2,0),""),10) -> 咨询费表
A72: fund_form | B72: =LEFT(IFERROR(VLOOKUP(A72,数据表!C:D,2,0),""),10) -> 诺诺宝申请表 | C72: user_product_detail | D72: =LEFT(IFERROR(VLOOKUP(C72,数据表!C:D,2,0),""),10) -> 购买产品明细 | F72: =LEFT(IFERROR(VLOOKUP(E72,数据表!C:D,2,0),""),10) | G72: borrows_repayment | H72: =LEFT(IFERROR(VLOOKUP(G72,数据表!C:D,2,0),""),10) -> 借入者还款表
A73: debt_buy_relation_log | B73: =LEFT(IFERROR(VLOOKUP(A73,数据表!C:D,2,0),""),10) -> 债转购买关系记录表 | C73: userproduct_ratecard_relation | D73: =LEFT(IFERROR(VLOOKUP(C73,数据表!C:D,2,0),""),10) | F73: =LEFT(IFERROR(VLOOKUP(E73,数据表!C:D,2,0),""),10) | G73: borrows_guarantee | H73: =LEFT(IFERROR(VLOOKUP(G73,数据表!C:D,2,0),""),10) -> 借入者代偿表
A74: lazy_add | B74: =LEFT(IFERROR(VLOOKUP(A74,数据表!C:D,2,0),""),10) -> 精选计划续投记录 | D74: =LEFT(IFERROR(VLOOKUP(C74,数据表!C:D,2,0),""),10) | F74: =LEFT(IFERROR(VLOOKUP(E74,数据表!C:D,2,0),""),10) | H74: =LEFT(IFERROR(VLOOKUP(G74,数据表!C:D,2,0),""),10)
A75: debt_batch_buy_log | B75: =LEFT(IFERROR(VLOOKUP(A75,数据表!C:D,2,0),""),10) -> 债权包购买历史记录表 | D75: =LEFT(IFERROR(VLOOKUP(C75,数据表!C:D,2,0),""),10) | F75: =LEFT(IFERROR(VLOOKUP(E75,数据表!C:D,2,0),""),10) | H75: =LEFT(IFERROR(VLOOKUP(G75,数据表!C:D,2,0),""),10)
B76: =LEFT(IFERROR(VLOOKUP(A76,数据表!C:D,2,0),""),10) | D76: =LEFT(IFERROR(VLOOKUP(C76,数据表!C:D,2,0),""),10) | F76: =LEFT(IFERROR(VLOOKUP(E76,数据表!C:D,2,0),""),10) | H76: =LEFT(IFERROR(VLOOKUP(G76,数据表!C:D,2,0),""),10)
A77: 账户 | B77: =LEFT(IFERROR(VLOOKUP(A77,数据表!C:D,2,0),""),10) | D77: =LEFT(IFERROR(VLOOKUP(C77,数据表!C:D,2,0),""),10) | F77: =LEFT(IFERROR(VLOOKUP(E77,数据表!C:D,2,0),""),10) | G77: 贷后 | H77: =LEFT(IFERROR(VLOOKUP(G77,数据表!C:D,2,0),""),10)
A78: finance_account | B78: =LEFT(IFERROR(VLOOKUP(A78,数据表!C:D,2,0),""),10) -> 资金帐户表 | C78: interest_info | D78: =LEFT(IFERROR(VLOOKUP(C78,数据表!C:D,2,0),""),10) -> 新的用户收益表 | F78: =LEFT(IFERROR(VLOOKUP(E78,数据表!C:D,2,0),""),10) | G78: borrows_outsource_dunning | H78: =LEFT(IFERROR(VLOOKUP(G78,数据表!C:D,2,0),""),10) -> 会员委外催收 原表m
A79: fund_account | B79: =LEFT(IFERROR(VLOOKUP(A79,数据表!C:D,2,0),""),10) -> 用户基金账户表 | C79: interest_info_detail | D79: =LEFT(IFERROR(VLOOKUP(C79,数据表!C:D,2,0),""),10) -> 收益详情，记录每笔投 | F79: =LEFT(IFERROR(VLOOKUP(E79,数据表!C:D,2,0),""),10) | G79: black_gray_list | H79: =LEFT(IFERROR(VLOOKUP(G79,数据表!C:D,2,0),""),10) -> 反欺诈黑灰名单库,用
A80: vip_account | B80: =LEFT(IFERROR(VLOOKUP(A80,数据表!C:D,2,0),""),10) -> 精选账户表 | C80: user_interest | D80: =LEFT(IFERROR(VLOOKUP(C80,数据表!C:D,2,0),""),10) -> 用户收益明细表 | F80: =LEFT(IFERROR(VLOOKUP(E80,数据表!C:D,2,0),""),10) | G80: black_gray_rule | H80: =LEFT(IFERROR(VLOOKUP(G80,数据表!C:D,2,0),""),10)
A81: finance_log | B81: =LEFT(IFERROR(VLOOKUP(A81,数据表!C:D,2,0),""),10) -> 资金日志表 | C81: user_account_trans_log | D81: =LEFT(IFERROR(VLOOKUP(C81,数据表!C:D,2,0),""),10) -> 账户余额资金流向信息 | F81: =LEFT(IFERROR(VLOOKUP(E81,数据表!C:D,2,0),""),10) | H81: =LEFT(IFERROR(VLOOKUP(G81,数据表!C:D,2,0),""),10)
A82: finance_operation | B82: =LEFT(IFERROR(VLOOKUP(A82,数据表!C:D,2,0),""),10) -> 资金操作表 | D82: =LEFT(IFERROR(VLOOKUP(C82,数据表!C:D,2,0),""),10) | F82: =LEFT(IFERROR(VLOOKUP(E82,数据表!C:D,2,0),""),10) | H82: =LEFT(IFERROR(VLOOKUP(G82,数据表!C:D,2,0),""),10)
A83: finance_operation_relation | B83: =LEFT(IFERROR(VLOOKUP(A83,数据表!C:D,2,0),""),10) -> 资金操作映射表 | D83: =LEFT(IFERROR(VLOOKUP(C83,数据表!C:D,2,0),""),10) | F83: =LEFT(IFERROR(VLOOKUP(E83,数据表!C:D,2,0),""),10) | H83: =LEFT(IFERROR(VLOOKUP(G83,数据表!C:D,2,0),""),10)
A84: finance_role | B84: =LEFT(IFERROR(VLOOKUP(A84,数据表!C:D,2,0),""),10) -> 资金角色表 | D84: =LEFT(IFERROR(VLOOKUP(C84,数据表!C:D,2,0),""),10) | F84: =LEFT(IFERROR(VLOOKUP(E84,数据表!C:D,2,0),""),10) | H84: =LEFT(IFERROR(VLOOKUP(G84,数据表!C:D,2,0),""),10)
B85: =LEFT(IFERROR(VLOOKUP(A85,数据表!C:D,2,0),""),10) | D85: =LEFT(IFERROR(VLOOKUP(C85,数据表!C:D,2,0),""),10) | F85: =LEFT(IFERROR(VLOOKUP(E85,数据表!C:D,2,0),""),10) | H85: =LEFT(IFERROR(VLOOKUP(G85,数据表!C:D,2,0),""),10)
B86: =LEFT(IFERROR(VLOOKUP(A86,数据表!C:D,2,0),""),10) | D86: =LEFT(IFERROR(VLOOKUP(C86,数据表!C:D,2,0),""),10) | F86: =LEFT(IFERROR(VLOOKUP(E86,数据表!C:D,2,0),""),10) | H86: =LEFT(IFERROR(VLOOKUP(G86,数据表!C:D,2,0),""),10)
A87: 投资兑付 | B87: =LEFT(IFERROR(VLOOKUP(A87,数据表!C:D,2,0),""),10) | D87: =LEFT(IFERROR(VLOOKUP(C87,数据表!C:D,2,0),""),10) | F87: =LEFT(IFERROR(VLOOKUP(E87,数据表!C:D,2,0),""),10) | H87: =LEFT(IFERROR(VLOOKUP(G87,数据表!C:D,2,0),""),10)
A88: vip_account | B88: =LEFT(IFERROR(VLOOKUP(A88,数据表!C:D,2,0),""),10) -> 精选账户表 | D88: =LEFT(IFERROR(VLOOKUP(C88,数据表!C:D,2,0),""),10) | F88: =LEFT(IFERROR(VLOOKUP(E88,数据表!C:D,2,0),""),10) | H88: =LEFT(IFERROR(VLOOKUP(G88,数据表!C:D,2,0),""),10)
A89: fund_redeem_form | B89: =LEFT(IFERROR(VLOOKUP(A89,数据表!C:D,2,0),""),10) -> 赎回表 | D89: =LEFT(IFERROR(VLOOKUP(C89,数据表!C:D,2,0),""),10) | F89: =LEFT(IFERROR(VLOOKUP(E89,数据表!C:D,2,0),""),10) | H89: =LEFT(IFERROR(VLOOKUP(G89,数据表!C:D,2,0),""),10)
A90: borrows_accept | B90: =LEFT(IFERROR(VLOOKUP(A90,数据表!C:D,2,0),""),10) -> 借出者收款表 | D90: =LEFT(IFERROR(VLOOKUP(C90,数据表!C:D,2,0),""),10) | F90: =LEFT(IFERROR(VLOOKUP(E90,数据表!C:D,2,0),""),10) | H90: =LEFT(IFERROR(VLOOKUP(G90,数据表!C:D,2,0),""),10)
A91: debt_accept | B91: =LEFT(IFERROR(VLOOKUP(A91,数据表!C:D,2,0),""),10) -> 债转收款表（只支持e | D91: =LEFT(IFERROR(VLOOKUP(C91,数据表!C:D,2,0),""),10) | F91: =LEFT(IFERROR(VLOOKUP(E91,数据表!C:D,2,0),""),10) | H91: =LEFT(IFERROR(VLOOKUP(G91,数据表!C:D,2,0),""),10)
B92: =LEFT(IFERROR(VLOOKUP(A92,数据表!C:D,2,0),""),10) | D92: =LEFT(IFERROR(VLOOKUP(C92,数据表!C:D,2,0),""),10) | F92: =LEFT(IFERROR(VLOOKUP(E92,数据表!C:D,2,0),""),10) | H92: =LEFT(IFERROR(VLOOKUP(G92,数据表!C:D,2,0),""),10)
B93: =LEFT(IFERROR(VLOOKUP(A93,数据表!C:D,2,0),""),10) | D93: =LEFT(IFERROR(VLOOKUP(C93,数据表!C:D,2,0),""),10) | F93: =LEFT(IFERROR(VLOOKUP(E93,数据表!C:D,2,0),""),10) | H93: =LEFT(IFERROR(VLOOKUP(G93,数据表!C:D,2,0),""),10)
A94: 提现 | B94: =LEFT(IFERROR(VLOOKUP(A94,数据表!C:D,2,0),""),10) | D94: =LEFT(IFERROR(VLOOKUP(C94,数据表!C:D,2,0),""),10) | F94: =LEFT(IFERROR(VLOOKUP(E94,数据表!C:D,2,0),""),10) | H94: =LEFT(IFERROR(VLOOKUP(G94,数据表!C:D,2,0),""),10)
A95: withdraw_cash | B95: =LEFT(IFERROR(VLOOKUP(A95,数据表!C:D,2,0),""),10) -> 提现申请表 | C95: user_withdraw_money_log | D95: =LEFT(IFERROR(VLOOKUP(C95,数据表!C:D,2,0),""),10) -> 用户提现日志信息管理 | F95: =LEFT(IFERROR(VLOOKUP(E95,数据表!C:D,2,0),""),10) | H95: =LEFT(IFERROR(VLOOKUP(G95,数据表!C:D,2,0),""),10)
A96: withdraw_cash_alipay | B96: =LEFT(IFERROR(VLOOKUP(A96,数据表!C:D,2,0),""),10) -> 支付宝提现表 | C96: withdraw_reward | D96: =LEFT(IFERROR(VLOOKUP(C96,数据表!C:D,2,0),""),10) | F96: =LEFT(IFERROR(VLOOKUP(E96,数据表!C:D,2,0),""),10) | H96: =LEFT(IFERROR(VLOOKUP(G96,数据表!C:D,2,0),""),10)
B97: =LEFT(IFERROR(VLOOKUP(A97,数据表!C:D,2,0),""),10) | D97: =LEFT(IFERROR(VLOOKUP(C97,数据表!C:D,2,0),""),10) | F97: =LEFT(IFERROR(VLOOKUP(E97,数据表!C:D,2,0),""),10) | H97: =LEFT(IFERROR(VLOOKUP(G97,数据表!C:D,2,0),""),10)
A98: 券 | B98: =LEFT(IFERROR(VLOOKUP(A98,数据表!C:D,2,0),""),10) | D98: =LEFT(IFERROR(VLOOKUP(C98,数据表!C:D,2,0),""),10) | F98: =LEFT(IFERROR(VLOOKUP(E98,数据表!C:D,2,0),""),10) | H98: =LEFT(IFERROR(VLOOKUP(G98,数据表!C:D,2,0),""),10)
A99: bank_code | B99: =LEFT(IFERROR(VLOOKUP(A99,数据表!C:D,2,0),""),10) -> 镑客码 对应原数据库 | D99: =LEFT(IFERROR(VLOOKUP(C99,数据表!C:D,2,0),""),10) | F99: =LEFT(IFERROR(VLOOKUP(E99,数据表!C:D,2,0),""),10) | H99: =LEFT(IFERROR(VLOOKUP(G99,数据表!C:D,2,0),""),10)
A100: coupon_use | B100: =LEFT(IFERROR(VLOOKUP(A100,数据表!C:D,2,0),""),10) -> 券的使用情况，原表i | D100: =LEFT(IFERROR(VLOOKUP(C100,数据表!C:D,2,0),""),10) | F100: =LEFT(IFERROR(VLOOKUP(E100,数据表!C:D,2,0),""),10) | H100: =LEFT(IFERROR(VLOOKUP(G100,数据表!C:D,2,0),""),10)
...

Sheet Sheet5
H2: WHERE user_id=@user_id limit 10;
H3: limit 10;
B4: SELECT * FROM | C4: activity_vip | D4: WHERE user_id=@user_id limit 10;
B5: SELECT * FROM | C5: activity_vip_label | D5: WHERE user_id=@user_id limit 10;
B6: SELECT * FROM | C6: activity_vip_physicalgoods | D6: WHERE user_id=@user_id limit 10;
B7: SELECT * FROM | C7: activity_vip_physicalgoods_info | D7: WHERE user_id=@user_id limit 10;
B8: SELECT * FROM | C8: activity_vip_praise_log | D8: WHERE user_id=@user_id limit 10;
B9: SELECT * FROM | C9: activity_vip_virtualgoods | D9: WHERE user_id=@user_id limit 10;
B10: SELECT * FROM | C10: activity_point_log | D10: WHERE user_id=@user_id limit 10;
B11: SELECT * FROM | C11: activity_prize_gain_list | D11: WHERE user_id=@user_id limit 10;
B12: SELECT * FROM | C12: activity_prize_list | D12: WHERE user_id=@user_id limit 10;

Sheet 资金账户
A1: 订单 | B1: 产品账户 | C1: 资金账户 | D1: 资金账户区别
A2: borrows_bidding | B2: user_info | C2: finance_account | D2: 7
A3: debt_buy_log | B3: user_info | C3: finance_account | D3: 7
A4: vip_form | B4: vip_account | C4: finance_account | D4: 13
A5: fund_form | B5: fund_account | C5: finance_account | D5: 27/35
A6: trans_detail | B6: user_info | C6: finance_account | D6: 42
A7: user_product | B7: merchant_regular_account | C7: finance_account | D7: 43

Sheet 计划类产品
A1: 精选计划
A6: 贴心计划
